winhotkey/ThreadedUvicorn.py
winhotkey/__about__.py
winhotkey/__init__.py
winhotkey/__main__.py
winhotkey/dummy_keyboard.py
winhotkey/keyboard_wrappers.py
winhotkey/cli/__init__.py
winhotkey/documentation/cli_demo.gif
winhotkey/documentation/full_demo.gif
winhotkey/documentation/setting_hotkeys.gif
winhotkey/documentation/starting_gui.gif
winhotkey/web/__init__.py
winhotkey/web/static/css/custom.css
winhotkey/web/static/css/jquery.toast.min.css
winhotkey/web/static/css/normalize.css
winhotkey/web/static/css/skeleton.css
winhotkey/web/static/images/favicon.ico
winhotkey/web/static/js/jquery.toast.min.js
winhotkey/web/static/js/winhotkey.js
winhotkey/web/static/pages/home.html
winhotkey-0.0.3.dist-info/METADATA
winhotkey-0.0.3.dist-info/WHEEL
winhotkey-0.0.3.dist-info/entry_points.txt
winhotkey-0.0.3.dist-info/licenses/LICENSE.txt
winhotkey-0.0.3.dist-info/RECORD
