Metadata-Version: 2.1
Name: winhotkey
Version: 0.0.3
Project-URL: Documentation, https://github.com/richmr/winhotkey#readme
Project-URL: Issues, https://github.com/richmr/winhotkey/issues
Project-URL: Source, https://github.com/richmr/winhotkey
Author-email: richmr <richmr@users.noreply.github.com>
License-Expression: MIT
License-File: LICENSE.txt
Classifier: Development Status :: 4 - Beta
Classifier: Programming Language :: Python
Classifier: Programming Language :: Python :: 3.11
Classifier: Programming Language :: Python :: Implementation :: CPython
Classifier: Programming Language :: Python :: Implementation :: PyPy
Requires-Python: >=3.11
Requires-Dist: fastapi
Requires-Dist: keyboard
Requires-Dist: pydantic
Requires-Dist: typer[all]
Requires-Dist: uvicorn[standard]
